netio_pdu_control/NetioClient.py
netio_pdu_control/__init__.py
netio_pdu_control/__main__.py
netio_pdu_control-0.0.6.dist-info/LICENSE
netio_pdu_control-0.0.6.dist-info/METADATA
netio_pdu_control-0.0.6.dist-info/WHEEL
netio_pdu_control-0.0.6.dist-info/top_level.txt
netio_pdu_control-0.0.6.dist-info/RECORD
