Metadata-Version: 2.1
Name: netio-pdu-control
Version: 0.0.6
Summary: Library to control NETIO PowerPDU over the network
Home-page: https://gitlab.pic.es/ifaecontrol/netio-pdu-control
Author: IFAE
Author-email: aperezj@ifae.es
License: UNKNOWN
Project-URL: Bug Tracker, https://gitlab.pic.es/ifaecontrol/netio-pdu-control/-/issues
Platform: UNKNOWN
Classifier: Programming Language :: Python :: 3
Classifier: License :: OSI Approved :: MIT License
Classifier: Operating System :: OS Independent
Requires-Python: >=3.6
License-File: LICENSE
Requires-Dist: requests
Requires-Dist: xdg
